support_dh/__init__.py
support_dh/path.py
support_dh/setting.py
support_dh/sort.py
support_dh-0.0.13.dist-info/METADATA
support_dh-0.0.13.dist-info/WHEEL
support_dh-0.0.13.dist-info/top_level.txt
support_dh-0.0.13.dist-info/RECORD
