Metadata-Version: 2.2
Name: support-dh
Version: 0.0.13
Summary: decorate text, etc
Home-page: https://github.com/astatinegithub/support-dh.git
Author: astatine
Author-email: astatine.147@gmail.com
Requires-Python: >=3.9.13
Requires-Dist: setuptools>=63.4.1
Dynamic: author
Dynamic: author-email
Dynamic: description
Dynamic: description-content-type
Dynamic: home-page
Dynamic: requires-dist
Dynamic: requires-python
Dynamic: summary
